MANIFEST.in
README.rst
setup.py
django_responsive_viewer/__init__.py
django_responsive_viewer/admin.py
django_responsive_viewer/models.py
django_responsive_viewer/tests.py
django_responsive_viewer/urls.py
django_responsive_viewer/views.py
django_responsive_viewer.egg-info/PKG-INFO
django_responsive_viewer.egg-info/SOURCES.txt
django_responsive_viewer.egg-info/dependency_links.txt
django_responsive_viewer.egg-info/top_level.txt
django_responsive_viewer/static/js/jquery-1.11.3.js
django_responsive_viewer/templates/django_responsive_viewer/listing.html