Metadata-Version: 1.1
Name: django-responsive-viewer
Version: 0.1.1
Summary: A simple Django that will show differenct resolution of your page
Home-page: UNKNOWN
Author: Tim Hsu
Author-email: tim.yellow@gmail.com
License: BSD License
Platform: UNKNOWN
Classifier: Environment :: Web Environment
Classifier: Framework :: Django
Classifier: Intended Audience :: Developers
Classifier: License :: OSI Approved :: BSD License
Classifier: Operating System :: OS Independent
Classifier: Programming Language :: Python
